kurses/__init__.py
kurses/colors.py
kurses/font_resources.py
kurses/term.py
kurses/texture_surface.py
kurses/backend/__init__.py
kurses/backend/pygame.py
kurses/backend/sdl2/__init__.py
kurses/backend/sdl2/font_resources.py
kurses/backend/sdl2/texture_surface.py
kurses/events/__init__.py
kurses/stream/__init__.py
kurses/stream/attributes.py
kurses/stream/buffer.py
kurses/stream/low.py
kurses_py-0.1.1.4.data/data/LICENSE
kurses_py-0.1.1.4.data/data/README.md
kurses_py-0.1.1.4.data/data/docs/requirements.txt
kurses_py-0.1.1.4.data/data/examples/ModernDOS8x16.ttf
kurses_py-0.1.1.4.data/data/examples/asteroids.py
kurses_py-0.1.1.4.data/data/examples/editorial.py
kurses_py-0.1.1.4.data/data/examples/hello_world.py
kurses_py-0.1.1.4.data/data/examples/keypressed.py
kurses_py-0.1.1.4.data/data/examples/runtime_target_example.py
kurses_py-0.1.1.4.data/data/examples/snake.py
kurses_py-0.1.1.4.data/data/examples/testing.py
kurses_py-0.1.1.4.data/data/examples/ttf_cache_texture.py
kurses_py-0.1.1.4.data/data/examples/virtual_buffer.py
kurses_py-0.1.1.4.data/scripts/asteroids.py
kurses_py-0.1.1.4.data/scripts/hello_world.py
kurses_py-0.1.1.4.data/scripts/keypressed.py
kurses_py-0.1.1.4.data/scripts/runtime_target_example.py
kurses_py-0.1.1.4.data/scripts/testing.py
kurses_py-0.1.1.4.data/scripts/ttf_cache_texture.py
kurses_py-0.1.1.4.data/scripts/virtual_buffer.py
kurses_py-0.1.1.4.dist-info/LICENSE
kurses_py-0.1.1.4.dist-info/METADATA
kurses_py-0.1.1.4.dist-info/WHEEL
kurses_py-0.1.1.4.dist-info/top_level.txt
kurses_py-0.1.1.4.dist-info/RECORD
