Metadata-Version: 2.1
Name: kurses-py
Version: 0.1.1.4
Summary: This module simulates the ‘conio’ and ‘curses’ libraries to create text interfaces with color and cursor.
Home-page: https://github.com/SealtielFreak/kurses.py
Author: SealtielFreak
Author-email: sealtielfreak@yandex.com
License: LGPL 2.1
Requires-Python: >=3.8
License-File: LICENSE
